_version.py
pychumpchem/__init__.py
pychumpchem/_base.py
pychumpchem/cli.py
pychumpchem/units.py
pychumpchem/engine/__init__.py
pychumpchem/engine/orca/__init__.py
pychumpchem/engine/orca/_dataclasses.py
pychumpchem/engine/orca/_orcablocks.py
pychumpchem/engine/orca/_renderer.py
pychumpchem/engine/orca/_validators.py
pychumpchem/engine/orca/config_loader.py
pychumpchem/engine/orca/input_generator.py
tests/data/villi.inp
tests/orca/test_coord.py
tests/orca/test_extra.py
tests/orca/test_geom_scan.py
tests/orca/test_neb.py
tests/orca/test_extra/extra.toml
tests/test_orca/neb.toml
tests/test_orca/opt_scan.toml
tests/test_orca/orca.inp
tests/test_orca/orca_parse.py
pychumpchem-0.0.1.dist-info/METADATA
pychumpchem-0.0.1.dist-info/WHEEL
pychumpchem-0.0.1.dist-info/licenses/LICENSE
pychumpchem-0.0.1.dist-info/RECORD
