Metadata-Version: 2.3
Name: pychumpchem
Version: 0.0.1
Summary: Input file generators for computational chemistry
Project-URL: Documentation, https://github.com/HaoZeke/pychumpchem#readme
Project-URL: Issues, https://github.com/HaoZeke/pychumpchem/issues
Project-URL: Source, https://github.com/HaoZeke/pychumpchem
Author-email: Rohit Goswami <rog32@hi.is>
License: MIT
Keywords: compchem,config
Classifier: Development Status :: 4 - Beta
Classifier: Programming Language :: Python
Classifier: Programming Language :: Python :: 3 :: Only
Classifier: Programming Language :: Python :: 3.9
Classifier: Programming Language :: Python :: 3.10
Classifier: Programming Language :: Python :: 3.11
Classifier: Programming Language :: Python :: 3.12
Classifier: Programming Language :: Python :: Implementation :: CPython
Requires-Python: >=3.10
Requires-Dist: jinja2>=3.1.2
Requires-Dist: numpy>=1.26.2
Requires-Dist: pint>=0.22
Requires-Dist: tomli>=2.0.1
Provides-Extra: cli
Requires-Dist: click>=8.1.7; extra == 'cli'
Provides-Extra: doc
Requires-Dist: mdit-py-plugins>=0.3.4; extra == 'doc'
Requires-Dist: myst-nb>=1; extra == 'doc'
Requires-Dist: myst-parser>=2; extra == 'doc'
Requires-Dist: sphinx-autodoc2>=0.5; extra == 'doc'
Requires-Dist: sphinx-copybutton>=0.5.2; extra == 'doc'
Requires-Dist: sphinx-library>=1.1.2; extra == 'doc'
Requires-Dist: sphinx-sitemap>=2.5.1; extra == 'doc'
Requires-Dist: sphinx-togglebutton>=0.3.2; extra == 'doc'
Requires-Dist: sphinx>=7.2.6; extra == 'doc'
Requires-Dist: sphinxcontrib-apidoc>=0.4; extra == 'doc'
